tmp_env/bin/rst2html.py
tmp_env/bin/rst2html4.py
tmp_env/bin/rst2html5.py
tmp_env/bin/rst2latex.py
tmp_env/bin/rst2man.py
tmp_env/bin/rst2odt.py
tmp_env/bin/rst2odt_prepstyles.py
tmp_env/bin/rst2pseudoxml.py
tmp_env/bin/rst2s5.py
tmp_env/bin/rst2xetex.py
tmp_env/bin/rst2xml.py
tmp_env/bin/rstpep2html.py
my_minipack_sojung-1.0.0.dist-info/LICENSE
my_minipack_sojung-1.0.0.dist-info/METADATA
my_minipack_sojung-1.0.0.dist-info/WHEEL
my_minipack_sojung-1.0.0.dist-info/top_level.txt
my_minipack_sojung-1.0.0.dist-info/RECORD
