Metadata-Version: 2.1
Name: my_minipack_sojung
Version: 1.0.0
Summary: Howto create a package in python.
Author-email: sojung <sojung@student.42.fr>
License: MIT License
Keywords: Education,Package,HowTo
Classifier: Development Status :: 3 - Alpha
Classifier: Intended Audience :: Developers
Classifier: Intended Audience :: Education
Classifier: License :: OSI Approved :: MIT License
Classifier: Programming Language :: Python :: 3
Classifier: Programming Language :: Python :: 3 :: Only
License-File: LICENSE
